adafruit_azureiot/__init__.py
adafruit_azureiot/base64.py
adafruit_azureiot/constants.py
adafruit_azureiot/device_registration.py
adafruit_azureiot/hmac.py
adafruit_azureiot/iot_error.py
adafruit_azureiot/iot_mqtt.py
adafruit_azureiot/iotcentral_device.py
adafruit_azureiot/iothub_device.py
adafruit_azureiot/keys.py
adafruit_azureiot/quote.py
adafruit_circuitpython_azureiot-3.0.3.dist-info/licenses/LICENSE
adafruit_circuitpython_azureiot-3.0.3.dist-info/METADATA
adafruit_circuitpython_azureiot-3.0.3.dist-info/WHEEL
adafruit_circuitpython_azureiot-3.0.3.dist-info/top_level.txt
adafruit_circuitpython_azureiot-3.0.3.dist-info/RECORD
