Metadata-Version: 2.4
Name: adafruit-circuitpython-azureiot
Version: 3.0.3
Summary: Access to Microsoft Azure IoT from CircuitPython
Author-email: Adafruit Industries <circuitpython@adafruit.com>
License: MIT
Project-URL: Homepage, https://github.com/adafruit/Adafruit_CircuitPython_AzureIoT
Keywords: adafruit,blinka,circuitpython,micropython,azureiot,azure,iot,device,services,,iothub,,iotcentral
Classifier: Intended Audience :: Developers
Classifier: Topic :: Software Development :: Libraries
Classifier: Topic :: Software Development :: Embedded Systems
Classifier: Topic :: System :: Hardware
Classifier: License :: OSI Approved :: MIT License
Classifier: Programming Language :: Python :: 3
License-File: LICENSE
Requires-Dist: Adafruit-Blinka
Requires-Dist: adafruit-circuitpython-logging>=4.0.1
Requires-Dist: adafruit-circuitpython-minimqtt
Requires-Dist: adafruit-circuitpython-binascii
Provides-Extra: optional
Dynamic: license-file
